gitreview_gpt/__init__.py
gitreview_gpt/__main__.py
gitreview_gpt/app.py
gitreview_gpt/formatter.py
gitreview_gpt/prompt.py
gitreview_gpt/request.py
gitreview_gpt/reviewer.py
gitreview_gpt/utils.py
gitreview_gpt-0.1.4.dist-info/LICENSE
gitreview_gpt-0.1.4.dist-info/METADATA
gitreview_gpt-0.1.4.dist-info/WHEEL
gitreview_gpt-0.1.4.dist-info/entry_points.txt
gitreview_gpt-0.1.4.dist-info/RECORD
