Metadata-Version: 2.1
Name: gitreview-gpt
Version: 0.1.4
Summary: CLI tool that reviews your git changes with GPT-3.5 and GPT-4
Author: fynnfluegge
Author-email: fynnfluegge@gmx.de
Requires-Python: >=3.8,<4.0
Classifier: Programming Language :: Python :: 3
Classifier: Programming Language :: Python :: 3.8
Classifier: Programming Language :: Python :: 3.9
Classifier: Programming Language :: Python :: 3.10
Classifier: Programming Language :: Python :: 3.11
Requires-Dist: tiktoken (>=0.4.0,<0.5.0)
Requires-Dist: yaspin (>=2.3.0,<3.0.0)
